{
    "public_id":  "EB-TM3828",
    "title":  "Casa en esquina en Sendero las Moras",
    "description":  "Casa en esquina en Sendero las Moras, ubicada a espaldas de Galerias Santa Anita, un coto que te brinda seguridad y tranquilidad!\n\n\nPLANTA BAJA:\n-Cochera 2 autos\n-Entrada principal con puerta de parota\n-Estudio\n-Medio baño \n-Cuarto de lavado\n-Area amplia de sala y comedor\n-Cocina integral equipada, barra desayunadora y cubierta de granito\n-Patio interior con jardinera\n-Entrada lateral\n-Jardin lateral\n\nSEGUNDO NIVEL:\n-3 Recamaras cada una con baño completo\n-Recamara principal con amplio vestidor\n-Las 2 recamaras principales con closet y baño completo\n-Sala de Televisión\n\n191 mts2 de Terreno.\n240 mts2 de Construcción\nCisterna y tinaco\n\nEl coto cuenta con entrada controlada, seguridad 24/7, Alberca, areas verdes, gymnasio y terraza de usos multiples.",
    "bedrooms":  3,
    "bathrooms":  3,
    "half_bathrooms":  1,
    "parking_spaces":  2,
    "lot_size":  191.0,
    "construction_size":  240.0,
    "lot_length":  null,
    "lot_width":  null,
    "floors":  null,
    "floor":  null,
    "age":  "new_construction",
    "internal_id":  "GABOMORAS",
    "expenses":  null,
    "location":  {
                     "name":  "Sendero las Moras, Tlajomulco de Zúñiga, Jalisco",
                     "latitude":  20.5577882,
                     "longitude":  -103.4812553,
                     "street":  "VISTA A LA MONTAÑA",
                     "postal_code":  "45645",
                     "show_exact_location":  true,
                     "hide_exact_location":  false,
                     "exterior_number":  "3",
                     "interior_number":  null
                 },
    "property_type":  "Casa",
    "created_at":  "2025-06-24T14:46:07-03:00",
    "updated_at":  "2025-08-02T20:01:30-03:00",
    "published_at":  "2025-06-24T14:47:15-03:00",
    "operations":  [
                       {
                           "type":  "sale",
                           "amount":  5750000.0,
                           "currency":  "MXN",
                           "formatted_amount":  "$5,750,000",
                           "commission":  {
                                              "type":  "percentage",
                                              "value":  "4.0"
                                          },
                           "unit":  "total"
                       }
                   ],
    "property_files":  [

                       ],
    "videos":  [

               ],
    "virtual_tour":  null,
    "collaboration_notes":  null,
    "public_url":  "https://www.easybroker.com/mx/listings/casa-en-esquina-en-sendero-las-moras",
    "shared_commission_percentage":  null,
    "exclusive":  null,
    "foreclosure":  false,
    "tags":  [

             ],
    "private_description":  null,
    "show_prices":  true,
    "share_commission":  true,
    "property_images":  [
                            {
                                "title":  null,
                                "url":  "https://assets.easybroker.com/property_images/5333828/92062430/EB-TM3828.jpg?version=1750790676"
                            },
                            {
                                "title":  null,
                                "url":  "https://assets.easybroker.com/property_images/5333828/92057807/EB-TM3828.jpg?version=1750790676"
                            },
                            {
                                "title":  null,
                                "url":  "https://assets.easybroker.com/property_images/5333828/92062705/EB-TM3828.jpg?version=1750790676"
                            },
                            {
                                "title":  null,
                                "url":  "https://assets.easybroker.com/property_images/5333828/92058126/EB-TM3828.jpg?version=1750790676"
                            },
                            {
                                "title":  null,
                                "url":  "https://assets.easybroker.com/property_images/5333828/92058128/EB-TM3828.jpg?version=1750790676"
                            },
                            {
                                "title":  null,
                                "url":  "https://assets.easybroker.com/property_images/5333828/92058130/EB-TM3828.jpg?version=1750790676"
                            },
                            {
                                "title":  null,
                                "url":  "https://assets.easybroker.com/property_images/5333828/92058131/EB-TM3828.jpg?version=1750790676"
                            },
                            {
                                "title":  null,
                                "url":  "https://assets.easybroker.com/property_images/5333828/92058132/EB-TM3828.jpg?version=1750790676"
                            },
                            {
                                "title":  null,
                                "url":  "https://assets.easybroker.com/property_images/5333828/92058158/EB-TM3828.jpg?version=1750790676"
                            },
                            {
                                "title":  null,
                                "url":  "https://assets.easybroker.com/property_images/5333828/92058159/EB-TM3828.jpg?version=1750790676"
                            },
                            {
                                "title":  null,
                                "url":  "https://assets.easybroker.com/property_images/5333828/92058161/EB-TM3828.jpg?version=1750790676"
                            },
                            {
                                "title":  null,
                                "url":  "https://assets.easybroker.com/property_images/5333828/92058168/EB-TM3828.jpg?version=1750790676"
                            },
                            {
                                "title":  null,
                                "url":  "https://assets.easybroker.com/property_images/5333828/92058177/EB-TM3828.jpg?version=1750790676"
                            },
                            {
                                "title":  null,
                                "url":  "https://assets.easybroker.com/property_images/5333828/92058178/EB-TM3828.jpg?version=1750790676"
                            },
                            {
                                "title":  null,
                                "url":  "https://assets.easybroker.com/property_images/5333828/92058289/EB-TM3828.jpg?version=1750790676"
                            },
                            {
                                "title":  null,
                                "url":  "https://assets.easybroker.com/property_images/5333828/92058290/EB-TM3828.jpg?version=1750790676"
                            },
                            {
                                "title":  null,
                                "url":  "https://assets.easybroker.com/property_images/5333828/92058292/EB-TM3828.jpg?version=1750790676"
                            },
                            {
                                "title":  null,
                                "url":  "https://assets.easybroker.com/property_images/5333828/92058293/EB-TM3828.jpg?version=1750790676"
                            },
                            {
                                "title":  null,
                                "url":  "https://assets.easybroker.com/property_images/5333828/92058294/EB-TM3828.jpg?version=1750790676"
                            },
                            {
                                "title":  null,
                                "url":  "https://assets.easybroker.com/property_images/5333828/92058295/EB-TM3828.jpg?version=1750790676"
                            },
                            {
                                "title":  null,
                                "url":  "https://assets.easybroker.com/property_images/5333828/92058296/EB-TM3828.jpg?version=1750790676"
                            },
                            {
                                "title":  null,
                                "url":  "https://assets.easybroker.com/property_images/5333828/92062455/EB-TM3828.jpg?version=1750790676"
                            },
                            {
                                "title":  null,
                                "url":  "https://assets.easybroker.com/property_images/5333828/92062457/EB-TM3828.jpg?version=1750790676"
                            },
                            {
                                "title":  null,
                                "url":  "https://assets.easybroker.com/property_images/5333828/92062792/EB-TM3828.jpg?version=1750790801"
                            },
                            {
                                "title":  null,
                                "url":  "https://assets.easybroker.com/property_images/5333828/92062797/EB-TM3828.jpg?version=1750790803"
                            },
                            {
                                "title":  null,
                                "url":  "https://assets.easybroker.com/property_images/5333828/92062799/EB-TM3828.jpg?version=1750790803"
                            },
                            {
                                "title":  null,
                                "url":  "https://assets.easybroker.com/property_images/5333828/92062867/EB-TM3828.jpg?version=1750790879"
                            }
                        ],
    "images":  [
                   {
                       "title":  null,
                       "url":  "https://assets.easybroker.com/property_images/5333828/92062430/EB-TM3828.jpg?version=1750790676"
                   },
                   {
                       "title":  null,
                       "url":  "https://assets.easybroker.com/property_images/5333828/92057807/EB-TM3828.jpg?version=1750790676"
                   },
                   {
                       "title":  null,
                       "url":  "https://assets.easybroker.com/property_images/5333828/92062705/EB-TM3828.jpg?version=1750790676"
                   },
                   {
                       "title":  null,
                       "url":  "https://assets.easybroker.com/property_images/5333828/92058126/EB-TM3828.jpg?version=1750790676"
                   },
                   {
                       "title":  null,
                       "url":  "https://assets.easybroker.com/property_images/5333828/92058128/EB-TM3828.jpg?version=1750790676"
                   },
                   {
                       "title":  null,
                       "url":  "https://assets.easybroker.com/property_images/5333828/92058130/EB-TM3828.jpg?version=1750790676"
                   },
                   {
                       "title":  null,
                       "url":  "https://assets.easybroker.com/property_images/5333828/92058131/EB-TM3828.jpg?version=1750790676"
                   },
                   {
                       "title":  null,
                       "url":  "https://assets.easybroker.com/property_images/5333828/92058132/EB-TM3828.jpg?version=1750790676"
                   },
                   {
                       "title":  null,
                       "url":  "https://assets.easybroker.com/property_images/5333828/92058158/EB-TM3828.jpg?version=1750790676"
                   },
                   {
                       "title":  null,
                       "url":  "https://assets.easybroker.com/property_images/5333828/92058159/EB-TM3828.jpg?version=1750790676"
                   },
                   {
                       "title":  null,
                       "url":  "https://assets.easybroker.com/property_images/5333828/92058161/EB-TM3828.jpg?version=1750790676"
                   },
                   {
                       "title":  null,
                       "url":  "https://assets.easybroker.com/property_images/5333828/92058168/EB-TM3828.jpg?version=1750790676"
                   },
                   {
                       "title":  null,
                       "url":  "https://assets.easybroker.com/property_images/5333828/92058177/EB-TM3828.jpg?version=1750790676"
                   },
                   {
                       "title":  null,
                       "url":  "https://assets.easybroker.com/property_images/5333828/92058178/EB-TM3828.jpg?version=1750790676"
                   },
                   {
                       "title":  null,
                       "url":  "https://assets.easybroker.com/property_images/5333828/92058289/EB-TM3828.jpg?version=1750790676"
                   },
                   {
                       "title":  null,
                       "url":  "https://assets.easybroker.com/property_images/5333828/92058290/EB-TM3828.jpg?version=1750790676"
                   },
                   {
                       "title":  null,
                       "url":  "https://assets.easybroker.com/property_images/5333828/92058292/EB-TM3828.jpg?version=1750790676"
                   },
                   {
                       "title":  null,
                       "url":  "https://assets.easybroker.com/property_images/5333828/92058293/EB-TM3828.jpg?version=1750790676"
                   },
                   {
                       "title":  null,
                       "url":  "https://assets.easybroker.com/property_images/5333828/92058294/EB-TM3828.jpg?version=1750790676"
                   },
                   {
                       "title":  null,
                       "url":  "https://assets.easybroker.com/property_images/5333828/92058295/EB-TM3828.jpg?version=1750790676"
                   },
                   {
                       "title":  null,
                       "url":  "https://assets.easybroker.com/property_images/5333828/92058296/EB-TM3828.jpg?version=1750790676"
                   },
                   {
                       "title":  null,
                       "url":  "https://assets.easybroker.com/property_images/5333828/92062455/EB-TM3828.jpg?version=1750790676"
                   },
                   {
                       "title":  null,
                       "url":  "https://assets.easybroker.com/property_images/5333828/92062457/EB-TM3828.jpg?version=1750790676"
                   },
                   {
                       "title":  null,
                       "url":  "https://assets.easybroker.com/property_images/5333828/92062792/EB-TM3828.jpg?version=1750790801"
                   },
                   {
                       "title":  null,
                       "url":  "https://assets.easybroker.com/property_images/5333828/92062797/EB-TM3828.jpg?version=1750790803"
                   },
                   {
                       "title":  null,
                       "url":  "https://assets.easybroker.com/property_images/5333828/92062799/EB-TM3828.jpg?version=1750790803"
                   },
                   {
                       "title":  null,
                       "url":  "https://assets.easybroker.com/property_images/5333828/92062867/EB-TM3828.jpg?version=1750790879"
                   }
               ],
    "agent":  {
                  "id":  391012,
                  "name":  "Lic.Gabriela Martínez",
                  "full_name":  "Lic.Gabriela Martínez",
                  "mobile_phone":  "+523338087984",
                  "profile_image_url":  "https://assets.easybroker.com/profile_images/391012/IMG_0527__scaled_.jpeg?version=1757459148",
                  "email":  "GABRIELAMTZ6@HOTMAIL.COM"
              },
    "features":  [
                     {
                         "name":  "Cisterna",
                         "category":  "Exterior"
                     },
                     {
                         "name":  "Facilidad para estacionarse",
                         "category":  "Exterior"
                     },
                     {
                         "name":  "Jardín",
                         "category":  "Exterior"
                     },
                     {
                         "name":  "Riego por aspersión",
                         "category":  "Exterior"
                     },
                     {
                         "name":  "Cocina equipada",
                         "category":  "General"
                     },
                     {
                         "name":  "Cocina integral",
                         "category":  "General"
                     },
                     {
                         "name":  "Cuarto de servicio",
                         "category":  "General"
                     },
                     {
                         "name":  "Dos plantas",
                         "category":  "General"
                     },
                     {
                         "name":  "Estudio",
                         "category":  "General"
                     },
                     {
                         "name":  "Fraccionamiento privado",
                         "category":  "General"
                     },
                     {
                         "name":  "Seguridad 24 horas",
                         "category":  "General"
                     },
                     {
                         "name":  "Alberca",
                         "category":  "Recreación"
                     },
                     {
                         "name":  "Área de juegos infantiles",
                         "category":  "Recreación"
                     },
                     {
                         "name":  "Gimnasio",
                         "category":  "Recreación"
                     },
                     {
                         "name":  "Salón de usos múltiples",
                         "category":  "Recreación"
                     }
                 ]
}
