{
    "public_id":  "EB-DC4791",
    "title":  "TERRENO  INDUSTRIAL,COMERCIAL, BODEGAS 15.8 HECTAREAS TALA-AMECA",
    "title_image_full":  "https://assets.easybroker.com/property_images/1074791/90560213/EB-DC4791.jpeg?version=1747929950",
    "title_image_thumb":  "https://assets.easybroker.com/property_images/1074791/90560213/EB-DC4791.jpeg?version=1747929950\u0026width=200",
    "location":  "Acacias, Tala, Jalisco",
    "operations":  [
                       {
                           "type":  "sale",
                           "amount":  950.0,
                           "currency":  "MXN",
                           "formatted_amount":  "$950",
                           "commission":  {
                                              "type":  "percentage",
                                              "value":  "5.0"
                                          },
                           "unit":  "square_meter"
                       },
                       {
                           "type":  "rental",
                           "amount":  3.0,
                           "currency":  "MXN",
                           "formatted_amount":  "$3",
                           "commission":  {
                                              "type":  "months",
                                              "value":  1
                                          },
                           "unit":  "square_meter"
                       }
                   ],
    "bedrooms":  null,
    "bathrooms":  null,
    "parking_spaces":  null,
    "property_type":  "Terreno",
    "lot_size":  null,
    "construction_size":  null,
    "updated_at":  "2025-08-22T12:34:11-06:00",
    "agent":  "Lic.Gabriela Martínez",
    "show_prices":  true,
    "share_commission":  true
}
