{
  "public_id": "EB-OR2225",
  "title": "EXCELENTE CASA EN COTO GUADALUPE INN ZAPOPAN",
  "title_image_full": "https://assets.easybroker.com/property_images/4082225/67516748/EB-OR2225.jpg?version=1697934786",
  "title_image_thumb": "https://assets.easybroker.com/property_images/4082225/67516748/EB-OR2225.jpg?version=1697934786&width=200",
  "location": "Guadalupe Inn, Zapopan, Jalisco",
  "operations": [
    {
      "type": "sale",
      "amount": 2690000.0,
      "currency": "MXN",
      "formatted_amount": "$2,690,000",
      "commission": {
        "type": "percentage"
      },
      "unit": "total"
    }
  ],
  "bedrooms": 3,
  "bathrooms": 2,
  "parking_spaces": 1,
  "property_type": "Casa en condominio",
  "lot_size": 66.0,
  "construction_size": 80.0,
  "updated_at": "2025-05-12T12:09:04-06:00",
  "agent": "Lic.Gabriela Martínez",
  "show_prices": true,
  "share_commission": true
}