{
  "public_id": "EB-TA3975",
  "title": "DEPARTAMENTO EN VENTA EN COLONIA VIRREYES  RESIDENCIAL, ZAPOPAN, TORRE LÍRICA",
  "description": "Departamentos en PREVENTA en Colonia Virreyes Residencial, Zapopan\n\nTORRE LÍRICA\nHasta un 20% de descuento\nEntregas Octubre 2026\nExcelente oportunidad de inversión en una de las mejores zonas de Zapopan rodeado de cotos como Villa Verona, Los Castaños, Colinas de los Virreyes, Las Cumbres, Vistas del Tule, entre otros.\n\nAmenidades:\nAlberca\nSala de juntas\nCocina \nLobby\nGym\nSocial lounge comedor\nBiblioteca\nZona Comercial\n\nDesde 46m2 hasta 101m2\n\n1 recamara\n1 baño\nCocina integral\nSala/Comedor\nLavandería \n1 cajón de estacionamiento\nde 44m2 a 47m2\n\nAv. cercanas: Av. Naciones Unidas, Av. Inglaterra, Av. Ignacio Vallarta, Av. Juan Palomar y Arias, Av. Universidad, Periférico Poniente.\nLugares cercanos: Club de golf Lomas Altas, Hospital Real San José Valle Real, Hospital Puerta de Hierro, Zona Andares, Universidad Autónoma de Guadalajara (UAG), Plaza Galerías, Clínica Innovare.\n\nConviértete en un inversionista destacado.",
  "bedrooms": 1,
  "bathrooms": 1,
  "half_bathrooms": null,
  "parking_spaces": 1,
  "lot_size": null,
  "construction_size": 46.0,
  "lot_length": null,
  "lot_width": null,
  "floors": null,
  "floor": null,
  "age": "under_construction",
  "internal_id": "YULVEQLIRICA",
  "expenses": null,
  "location": {
    "name": "Virreyes Residencial, Zapopan, Jalisco",
    "latitude": 20.697796,
    "longitude": -103.4462399,
    "street": "AV NACIONES UNIDAS",
    "postal_code": "45136",
    "show_exact_location": true,
    "hide_exact_location": false,
    "exterior_number": "7972",
    "interior_number": null
  },
  "property_type": "Departamento",
  "created_at": "2025-05-02T16:45:30-06:00",
  "updated_at": "2025-05-12T12:09:04-06:00",
  "published_at": "2025-05-02T16:58:04-06:00",
  "operations": [
    {
      "type": "sale",
      "amount": 3749000.0,
      "currency": "MXN",
      "formatted_amount": "$3,749,000",
      "commission": {
        "type": "percentage",
        "value": "3.0"
      },
      "unit": "total"
    }
  ],
  "property_files": [],
  "videos": [],
  "virtual_tour": null,
  "collaboration_notes": null,
  "public_url": "https://www.easybroker.com/mx/listings/departamento-en-venta-en-colonia-virreyes-residencial-zapopan-torre-lirica",
  "shared_commission_percentage": 50.0,
  "exclusive": null,
  "foreclosure": false,
  "tags": [],
  "private_description": null,
  "show_prices": true,
  "share_commission": true,
  "property_images": [
    {
      "title": null,
      "url": "https://assets.easybroker.com/property_images/5213975/89668197/EB-TA3975.jpeg?version=1746226610"
    },
    {
      "title": null,
      "url": "https://assets.easybroker.com/property_images/5213975/89668198/EB-TA3975.jpeg?version=1746226610"
    },
    {
      "title": null,
      "url": "https://assets.easybroker.com/property_images/5213975/89668199/EB-TA3975.jpeg?version=1746226610"
    },
    {
      "title": null,
      "url": "https://assets.easybroker.com/property_images/5213975/89668200/EB-TA3975.jpeg?version=1746226610"
    },
    {
      "title": null,
      "url": "https://assets.easybroker.com/property_images/5213975/89668201/EB-TA3975.jpeg?version=1746226610"
    },
    {
      "title": null,
      "url": "https://assets.easybroker.com/property_images/5213975/89668256/EB-TA3975.jpeg?version=1746226610"
    },
    {
      "title": null,
      "url": "https://assets.easybroker.com/property_images/5213975/89668257/EB-TA3975.jpeg?version=1746226610"
    },
    {
      "title": null,
      "url": "https://assets.easybroker.com/property_images/5213975/89668258/EB-TA3975.jpeg?version=1746226610"
    },
    {
      "title": null,
      "url": "https://assets.easybroker.com/property_images/5213975/89668260/EB-TA3975.jpeg?version=1746226610"
    },
    {
      "title": null,
      "url": "https://assets.easybroker.com/property_images/5213975/89668259/EB-TA3975.jpeg?version=1746226610"
    },
    {
      "title": null,
      "url": "https://assets.easybroker.com/property_images/5213975/89668261/EB-TA3975.jpeg?version=1746226610"
    },
    {
      "title": null,
      "url": "https://assets.easybroker.com/property_images/5213975/89668275/EB-TA3975.jpeg?version=1746226610"
    },
    {
      "title": null,
      "url": "https://assets.easybroker.com/property_images/5213975/89668276/EB-TA3975.jpeg?version=1746226610"
    },
    {
      "title": null,
      "url": "https://assets.easybroker.com/property_images/5213975/89668277/EB-TA3975.jpeg?version=1746226610"
    },
    {
      "title": null,
      "url": "https://assets.easybroker.com/property_images/5213975/89668303/EB-TA3975.jpeg?version=1746226610"
    },
    {
      "title": null,
      "url": "https://assets.easybroker.com/property_images/5213975/89668304/EB-TA3975.jpeg?version=1746226610"
    },
    {
      "title": null,
      "url": "https://assets.easybroker.com/property_images/5213975/89668305/EB-TA3975.jpeg?version=1746226610"
    },
    {
      "title": null,
      "url": "https://assets.easybroker.com/property_images/5213975/89668307/EB-TA3975.jpeg?version=1746226610"
    },
    {
      "title": null,
      "url": "https://assets.easybroker.com/property_images/5213975/89668769/EB-TA3975.jpeg?version=1746226610"
    },
    {
      "title": null,
      "url": "https://assets.easybroker.com/property_images/5213975/89668770/EB-TA3975.jpeg?version=1746226610"
    },
    {
      "title": null,
      "url": "https://assets.easybroker.com/property_images/5213975/89668768/EB-TA3975.jpeg?version=1746226610"
    },
    {
      "title": null,
      "url": "https://assets.easybroker.com/property_images/5213975/89668772/EB-TA3975.jpeg?version=1746226610"
    },
    {
      "title": null,
      "url": "https://assets.easybroker.com/property_images/5213975/89668774/EB-TA3975.jpeg?version=1746226610"
    },
    {
      "title": null,
      "url": "https://assets.easybroker.com/property_images/5213975/89668773/EB-TA3975.jpeg?version=1746226610"
    },
    {
      "title": null,
      "url": "https://assets.easybroker.com/property_images/5213975/89668775/EB-TA3975.jpeg?version=1746226610"
    }
  ],
  "images": [
    {
      "title": null,
      "url": "https://assets.easybroker.com/property_images/5213975/89668197/EB-TA3975.jpeg?version=1746226610"
    },
    {
      "title": null,
      "url": "https://assets.easybroker.com/property_images/5213975/89668198/EB-TA3975.jpeg?version=1746226610"
    },
    {
      "title": null,
      "url": "https://assets.easybroker.com/property_images/5213975/89668199/EB-TA3975.jpeg?version=1746226610"
    },
    {
      "title": null,
      "url": "https://assets.easybroker.com/property_images/5213975/89668200/EB-TA3975.jpeg?version=1746226610"
    },
    {
      "title": null,
      "url": "https://assets.easybroker.com/property_images/5213975/89668201/EB-TA3975.jpeg?version=1746226610"
    },
    {
      "title": null,
      "url": "https://assets.easybroker.com/property_images/5213975/89668256/EB-TA3975.jpeg?version=1746226610"
    },
    {
      "title": null,
      "url": "https://assets.easybroker.com/property_images/5213975/89668257/EB-TA3975.jpeg?version=1746226610"
    },
    {
      "title": null,
      "url": "https://assets.easybroker.com/property_images/5213975/89668258/EB-TA3975.jpeg?version=1746226610"
    },
    {
      "title": null,
      "url": "https://assets.easybroker.com/property_images/5213975/89668260/EB-TA3975.jpeg?version=1746226610"
    },
    {
      "title": null,
      "url": "https://assets.easybroker.com/property_images/5213975/89668259/EB-TA3975.jpeg?version=1746226610"
    },
    {
      "title": null,
      "url": "https://assets.easybroker.com/property_images/5213975/89668261/EB-TA3975.jpeg?version=1746226610"
    },
    {
      "title": null,
      "url": "https://assets.easybroker.com/property_images/5213975/89668275/EB-TA3975.jpeg?version=1746226610"
    },
    {
      "title": null,
      "url": "https://assets.easybroker.com/property_images/5213975/89668276/EB-TA3975.jpeg?version=1746226610"
    },
    {
      "title": null,
      "url": "https://assets.easybroker.com/property_images/5213975/89668277/EB-TA3975.jpeg?version=1746226610"
    },
    {
      "title": null,
      "url": "https://assets.easybroker.com/property_images/5213975/89668303/EB-TA3975.jpeg?version=1746226610"
    },
    {
      "title": null,
      "url": "https://assets.easybroker.com/property_images/5213975/89668304/EB-TA3975.jpeg?version=1746226610"
    },
    {
      "title": null,
      "url": "https://assets.easybroker.com/property_images/5213975/89668305/EB-TA3975.jpeg?version=1746226610"
    },
    {
      "title": null,
      "url": "https://assets.easybroker.com/property_images/5213975/89668307/EB-TA3975.jpeg?version=1746226610"
    },
    {
      "title": null,
      "url": "https://assets.easybroker.com/property_images/5213975/89668769/EB-TA3975.jpeg?version=1746226610"
    },
    {
      "title": null,
      "url": "https://assets.easybroker.com/property_images/5213975/89668770/EB-TA3975.jpeg?version=1746226610"
    },
    {
      "title": null,
      "url": "https://assets.easybroker.com/property_images/5213975/89668768/EB-TA3975.jpeg?version=1746226610"
    },
    {
      "title": null,
      "url": "https://assets.easybroker.com/property_images/5213975/89668772/EB-TA3975.jpeg?version=1746226610"
    },
    {
      "title": null,
      "url": "https://assets.easybroker.com/property_images/5213975/89668774/EB-TA3975.jpeg?version=1746226610"
    },
    {
      "title": null,
      "url": "https://assets.easybroker.com/property_images/5213975/89668773/EB-TA3975.jpeg?version=1746226610"
    },
    {
      "title": null,
      "url": "https://assets.easybroker.com/property_images/5213975/89668775/EB-TA3975.jpeg?version=1746226610"
    }
  ],
  "agent": {
    "id": 391012,
    "name": "Lic.Gabriela Martínez",
    "full_name": "Lic.Gabriela Martínez",
    "mobile_phone": "+523338087984",
    "profile_image_url": "https://assets.easybroker.com/profile_images/391012/IMG_0527__scaled_.jpeg?version=1729887594",
    "email": "GABRIELAMTZ6@HOTMAIL.COM"
  },
  "features": [
    {
      "name": "Facilidad para estacionarse",
      "category": "Exterior"
    },
    {
      "name": "Cocina equipada",
      "category": "General"
    },
    {
      "name": "Cocina integral",
      "category": "General"
    },
    {
      "name": "Elevador",
      "category": "General"
    },
    {
      "name": "Fraccionamiento privado",
      "category": "General"
    },
    {
      "name": "Seguridad 24 horas",
      "category": "General"
    },
    {
      "name": "Mascotas permitidas",
      "category": "Políticas"
    },
    {
      "name": "Alberca",
      "category": "Recreación"
    },
    {
      "name": "Gimnasio",
      "category": "Recreación"
    },
    {
      "name": "Salón de usos múltiples",
      "category": "Recreación"
    }
  ]
}